scan_to_paperless/__init__.py
scan_to_paperless/add_code.py
scan_to_paperless/config.py
scan_to_paperless/config_schema.json
scan_to_paperless/jupyter.py
scan_to_paperless/jupyter_utils.py
scan_to_paperless/process.py
scan_to_paperless/process_schema.json
scan_to_paperless/process_schema.py
scan_to_paperless/process_utils.py
scan_to_paperless/py.typed
scan_to_paperless/scan.py
scan_to_paperless/scan_process_status.py
scan_to_paperless/scan_sane.py
scan_to_paperless/status.html
scan_to_paperless/status.py
scan_to_paperless-1.27.2.dist-info/LICENSE
scan_to_paperless-1.27.2.dist-info/METADATA
scan_to_paperless-1.27.2.dist-info/WHEEL
scan_to_paperless-1.27.2.dist-info/entry_points.txt
scan_to_paperless-1.27.2.dist-info/RECORD
