Metadata-Version: 2.3
Name: scan-to-paperless
Version: 1.27.2
Summary: Tool to scan and process documents to Paperless
License: BSD-2-Clause
Keywords: scan,paperless
Author: Stéphane Brunner
Author-email: stephane.brunner@gmail.com
Requires-Python: >=3.10
Classifier: Development Status :: 5 - Production/Stable
Classifier: Environment :: Console
Classifier: License :: OSI Approved :: BSD License
Classifier: Operating System :: OS Independent
Classifier: Programming Language :: Python
Classifier: Programming Language :: Python :: 3
Classifier: Programming Language :: Python :: 3.10
Classifier: Programming Language :: Python :: 3.11
Classifier: Programming Language :: Python :: 3.12
Classifier: Programming Language :: Python :: 3.13
Classifier: Typing :: Typed
Provides-Extra: jupyter
Provides-Extra: process
Provides-Extra: sane
Requires-Dist: Jinja2 ; extra == "process"
Requires-Dist: aiofiles
Requires-Dist: aiohttp
Requires-Dist: argcomplete
Requires-Dist: asyncinotify ; extra == "process"
Requires-Dist: cffi ; extra == "process"
Requires-Dist: deepmerge
Requires-Dist: deskew ; extra == "jupyter"
Requires-Dist: deskew ; extra == "process"
Requires-Dist: lxml
Requires-Dist: matplotlib ; extra == "jupyter"
Requires-Dist: matplotlib ; extra == "process"
Requires-Dist: natsort ; extra == "process"
Requires-Dist: nbformat ; extra == "process"
Requires-Dist: numpy ; extra == "process"
Requires-Dist: opencv-contrib-python-headless ; extra == "jupyter"
Requires-Dist: opencv-contrib-python-headless ; extra == "process"
Requires-Dist: pikepdf ; extra == "process"
Requires-Dist: pillow
Requires-Dist: polygon-math
Requires-Dist: pypdf ; extra == "process"
Requires-Dist: pyperclip
Requires-Dist: python-sane ; extra == "sane"
Requires-Dist: pyzbar ; extra == "process"
Requires-Dist: reportlab ; extra == "process"
Requires-Dist: requests ; extra == "process"
Requires-Dist: ruamel.yaml
Requires-Dist: scikit-image ; extra == "process"
Requires-Dist: sentry-sdk
Requires-Dist: types-aiofiles
Requires-Dist: typing-extensions
Requires-Dist: weasyprint ; extra == "process"
Requires-Dist: zxing-cpp ; extra == "process"
Project-URL: Bug Tracker, https://github.com/sbrunner/scan-to-paperless/issues
Project-URL: Homepage, https://hub.docker.com/r/sbrunner/scan-to-paperless/
Project-URL: Repository, https://github.com/sbrunner/scan-to-paperless
